setup.cfg
setup.py
opencache/__init__.py
opencache/node/__init__.py
opencache/node/opencachenode.py
opencache/node/server/__init__.py
opencache/node/server/opencachehttp.py
opencache/node/state/__init__.py
opencache/node/state/opencachemongodb.py
opencache_node.egg-info/PKG-INFO
opencache_node.egg-info/SOURCES.txt
opencache_node.egg-info/dependency_links.txt
opencache_node.egg-info/namespace_packages.txt
opencache_node.egg-info/requires.txt
opencache_node.egg-info/top_level.txt
scripts/opencache-node