Metadata-Version: 1.1
Name: opencache-node
Version: 0.1.0
Summary: Serve cached content in response to a user request.
Home-page: https://github.com/opencache-project/opencache-node
Author: Matthew Broadbent
Author-email: matt@matthewbroadbent.net
License: Apache License, Version 2.0
Download-URL: https://github.com/opencache-project/opencache-node/tarball/0.1.0
Keywords: content,caching,distribution,software defined networking
Platform: UNKNOWN
Classifier: Development Status :: 3 - Alpha
Classifier: Intended Audience :: Developers
Classifier: Intended Audience :: Science/Research
Classifier: License :: DFSG approved
Classifier: License :: OSI Approved :: Apache Software License
Classifier: Operating System :: POSIX
Classifier: Programming Language :: Python
Classifier: Topic :: System :: Networking
Classifier: Topic :: System :: Distributed Computing
Classifier: Topic :: System :: Logging
Classifier: Topic :: System :: Monitoring
